mlops/__init__.py
mlops/config.py
mlops/dataset.py
mlops/modeling/__init__.py
mlops/modeling/train.py
mlops_ivan_pleshakov-0.0.2.dist-info/METADATA
mlops_ivan_pleshakov-0.0.2.dist-info/WHEEL
mlops_ivan_pleshakov-0.0.2.dist-info/top_level.txt
mlops_ivan_pleshakov-0.0.2.dist-info/RECORD
