Metadata-Version: 2.1
Name: mlops-ivan-pleshakov
Version: 0.0.2
Summary: mlops misis
Author: IvanPleshakov
Classifier: Programming Language :: Python :: 3
Requires-Python: ~=3.10
